mojo/config/__init__.py
mojo/config/configurationformat.py
mojo/config/configurationloader.py
mojo/config/configurationmaps.py
mojo/config/configurationsettings.py
mojo/config/configurationvariables.py
mojo/config/cryptography.py
mojo/config/defaultvalues.py
mojo/config/normalize.py
mojo/config/optionoverrides.py
mojo/config/sources/__init__.py
mojo/config/sources/configurationsourcebase.py
mojo/config/sources/couchdbsource.py
mojo/config/sources/directorysource.py
mojo/config/sources/githubsource.py
mojo/config/sources/httpsource.py
mojo/config/sources/mongodbsource.py
mojo/config/synchronization/configsynchronizerbase.py
mojo/config/synchronization/couchdbconfigsynchronizer.py
mojo/config/synchronization/directoryconfigsynchronizer.py
mojo/config/synchronization/githubconfigsynchronizer.py
mojo/config/synchronization/mongodbconfigsynchronizer.py
mojo/config/wellknown.py
mojo_config-2.0.6.dist-info/LICENSE.txt
mojo_config-2.0.6.dist-info/METADATA
mojo_config-2.0.6.dist-info/WHEEL
mojo_config-2.0.6.dist-info/RECORD
